plone.recipe.zeoserver-3.0.5-py3.13-nspkg.pth
plone/recipe/zeoserver/__init__.py
plone/recipe/zeoserver/ctl.py
plone/recipe/zeoserver/pack.py
plone/recipe/zeoserver/recipe.py
plone/recipe/zeoserver/runzeo.bat
plone/recipe/zeoserver/zeoservice.py.in
plone/recipe/zeoserver/tests/__init__.py
plone/recipe/zeoserver/tests/test_docs.py
plone/recipe/zeoserver/tests/zeoserver.txt
plone_recipe_zeoserver-3.0.5.dist-info/METADATA
plone_recipe_zeoserver-3.0.5.dist-info/WHEEL
plone_recipe_zeoserver-3.0.5.dist-info/entry_points.txt
plone_recipe_zeoserver-3.0.5.dist-info/namespace_packages.txt
plone_recipe_zeoserver-3.0.5.dist-info/top_level.txt
plone_recipe_zeoserver-3.0.5.dist-info/RECORD
