Metadata-Version: 2.4
Name: plone.recipe.zeoserver
Version: 3.0.5
Summary: ZC Buildout recipe for installing a ZEO server
Home-page: https://github.com/plone/plone.recipe.zeoserver
Download-URL: https://pypi.org/project/plone.recipe.zeoserver
Author: Hanno Schlichting
Author-email: hannosch@plone.org
License: ZPL 2.1
Keywords: zope2 zeo zodb buildout
Classifier: Development Status :: 5 - Production/Stable
Classifier: License :: OSI Approved :: Zope Public License
Classifier: Framework :: Buildout
Classifier: Framework :: Plone
Classifier: Framework :: Plone :: 6.0
Classifier: Framework :: Plone :: 6.1
Classifier: Framework :: Zope
Classifier: Framework :: Zope :: 5
Classifier: Programming Language :: Python
Classifier: Programming Language :: Python :: 3.8
Classifier: Programming Language :: Python :: 3.9
Classifier: Programming Language :: Python :: 3.10
Classifier: Programming Language :: Python :: 3.11
Classifier: Programming Language :: Python :: 3.12
Classifier: Programming Language :: Python :: Implementation
Classifier: Programming Language :: Python :: Implementation :: CPython
Requires-Python: >=3.8
Requires-Dist: setuptools
Requires-Dist: zc.buildout
Requires-Dist: zc.recipe.egg
Requires-Dist: zdaemon
Requires-Dist: ZEO
Requires-Dist: ZODB>=5
Requires-Dist: zope.mkzeoinstance>=5.1.1
Requires-Dist: ZopeUndo
Provides-Extra: zrs
Requires-Dist: zc.zrs; extra == "zrs"
Dynamic: author
Dynamic: author-email
Dynamic: classifier
Dynamic: description
Dynamic: description-content-type
Dynamic: download-url
Dynamic: home-page
Dynamic: keywords
Dynamic: license
Dynamic: provides-extra
Dynamic: requires-dist
Dynamic: requires-python
Dynamic: summary
